sm_crypto/__init__.py
sm_crypto/ec.py
sm_crypto/sm2.py
sm_crypto/sm2_asn1.py
sm_crypto/sm3.py
sm_crypto/sm4.py
sm_crypto/utils.py
sm_crypto-0.1.1.dist-info/LICENSE
sm_crypto-0.1.1.dist-info/METADATA
sm_crypto-0.1.1.dist-info/WHEEL
sm_crypto-0.1.1.dist-info/top_level.txt
sm_crypto-0.1.1.dist-info/RECORD
