Metadata-Version: 2.1
Name: sm-crypto
Version: 0.1.1
Summary: china gm cryptography such as sm2,sm3,sm4
Home-page: https://github.com/hanzhichao/sm-crypto
Author: Han Zhichao
Author-email: superhin@126.com
License: MIT license
Keywords: sm-crypto,sm2,gm,sm3,sm4,gmssl
Classifier: Development Status :: 2 - Pre-Alpha
Classifier: Intended Audience :: Developers
Classifier: License :: OSI Approved :: MIT License
Classifier: Natural Language :: English
Classifier: Programming Language :: Python :: 3
Classifier: Programming Language :: Python :: 3.6
Classifier: Programming Language :: Python :: 3.7
Classifier: Programming Language :: Python :: 3.8
Requires-Python: >=3.6
License-File: LICENSE
Requires-Dist: pyasn1
